README.md
setup.cfg
setup.py
sas_pylogger_handler.egg-info/PKG-INFO
sas_pylogger_handler.egg-info/SOURCES.txt
sas_pylogger_handler.egg-info/dependency_links.txt
sas_pylogger_handler.egg-info/requires.txt
sas_pylogger_handler.egg-info/top_level.txt
src/__init__.py
src/sas_handler.py
test/test_sas_handler.py