Metadata-Version: 2.1
Name: sas-pylogger-handler
Version: 0.2.0
Summary: The SAS Python Logger Handler allows use the python logger system to send logging streams to SAS System logger
Home-page: https://github.com/a24lorie/sas-pylogger-handler
Author-email: a24lorie@gmail.com
License: GNU
Requires-Dist: saspy
